vietvoice/__init__.py
vietvoice/loader.py
vietvoice/predict.py
vietvoice/stft.py
vietvoice/symbol.py
vietvoice/train.py
vietvoice/vitext_to_phoneme.py
vietvoice/model/__init__.py
vietvoice/model/layers.py
vietvoice/model/predictor.py
vietvoice/model/tacotron2.py
vietvoice/model/trainer.py
vietvoice/utils/__init__.py
vietvoice/utils/config.py
vietvoice/utils/download_model.py
vietvoice/utils/logger.py
vietvoice/utils/lr_decay.py
vietvoice/utils/mask.py
vietvoice/utils/visualize.py
vietvoice-0.1.2.dist-info/METADATA
vietvoice-0.1.2.dist-info/WHEEL
vietvoice-0.1.2.dist-info/top_level.txt
vietvoice-0.1.2.dist-info/RECORD
